calc_lib_test/__init__.py
calc_lib_test/calc_lib_test.py
calc_lib_test-1.0.8.dist-info/METADATA
calc_lib_test-1.0.8.dist-info/WHEEL
calc_lib_test-1.0.8.dist-info/RECORD
